MANIFEST.in
README.md
setup.py
bin/pptop
pptop/__init__.py
pptop/core.py
pptop/exceptions.py
pptop/injection.py
pptop/logger.py
pptop/plugin.py
pptop.egg-info/PKG-INFO
pptop.egg-info/SOURCES.txt
pptop.egg-info/dependency_links.txt
pptop.egg-info/requires.txt
pptop.egg-info/top_level.txt
pptop/config/pptop.yml
pptop/config/scripts/hello.py
pptop/config/scripts/test1.py
pptop/plugins/__init__.py
pptop/plugins/asyncio.py
pptop/plugins/atasker.py
pptop/plugins/env.py
pptop/plugins/help.py
pptop/plugins/last_exception.py
pptop/plugins/log.py
pptop/plugins/malloc.py
pptop/plugins/neotasker.py
pptop/plugins/open_files.py
pptop/plugins/plugin_selector.py
pptop/plugins/script_runner.py
pptop/plugins/threads.py
pptop/plugins/vars.py
pptop/plugins/yappi.py
pptop/ui/__init__.py
pptop/ui/console.py
src/__pptop_injector.c