Metadata-Version: 2.1
Name: pptop
Version: 0.6.10
Summary: Open, extensible Python injector/profiler/analyzer
Home-page: https://pptop.io/
Author: Altertech
Author-email: div@altertech.com
License: MIT
Platform: UNKNOWN
Classifier: Programming Language :: Python :: 3
Classifier: License :: OSI Approved :: MIT License
Classifier: Topic :: Software Development :: Debuggers
Classifier: Topic :: Software Development :: Testing
